ipfindx/__init__.py
ipfindx/ipfindx.py
ipfindx-3.0.1.dist-info/licenses/LICENSE
ipfindx-3.0.1.dist-info/METADATA
ipfindx-3.0.1.dist-info/WHEEL
ipfindx-3.0.1.dist-info/entry_points.txt
ipfindx-3.0.1.dist-info/top_level.txt
ipfindx-3.0.1.dist-info/RECORD
