Metadata-Version: 2.4
Name: ipfindx
Version: 3.0.1
Summary: Advanced IP Intelligence Toolkit for cybersecurity professionals
Home-page: https://github.com/VritraSecz/IPFindX
Author: Alex Butler
License: MIT License
Project-URL: Homepage, https://github.com/VritraSecz/IPFindX
Project-URL: Bug Reports, https://github.com/VritraSecz/IPFindX/issues
Project-URL: Source, https://github.com/VritraSecz/IPFindX
Project-URL: Documentation, https://github.com/VritraSecz/IPFindX#readme
Project-URL: Website, https://vritrasec.com
Keywords: ip,intelligence,geolocation,osint,cybersecurity,network,security,threat-intelligence,ip-lookup,cybersec,infosec,penetration-testing
Platform: any
Classifier: Development Status :: 5 - Production/Stable
Classifier: Intended Audience :: Developers
Classifier: Intended Audience :: System Administrators
Classifier: Intended Audience :: Information Technology
Classifier: Topic :: Security
Classifier: Topic :: System :: Networking
Classifier: Topic :: Internet
Classifier: Topic :: Utilities
Classifier: License :: OSI Approved :: MIT License
Classifier: Programming Language :: Python :: 3
Classifier: Programming Language :: Python :: 3.7
Classifier: Programming Language :: Python :: 3.8
Classifier: Programming Language :: Python :: 3.9
Classifier: Programming Language :: Python :: 3.10
Classifier: Programming Language :: Python :: 3.11
Classifier: Programming Language :: Python :: 3.12
Classifier: Operating System :: OS Independent
Classifier: Operating System :: POSIX :: Linux
Classifier: Operating System :: Microsoft :: Windows
Classifier: Operating System :: MacOS
Classifier: Environment :: Console
Classifier: Natural Language :: English
Requires-Python: >=3.7
License-File: LICENSE
Requires-Dist: requests>=2.25.0
Requires-Dist: rich>=10.0.0
Dynamic: home-page
Dynamic: license-file
Dynamic: platform
Dynamic: requires-python
